pygremlinbox_ncgl_uk_2_0/__init__.py
pygremlinbox_ncgl_uk_2_0-1.4.0.dist-info/licenses/LICENCE
pygremlinbox_ncgl_uk_2_0-1.4.0.dist-info/METADATA
pygremlinbox_ncgl_uk_2_0-1.4.0.dist-info/WHEEL
pygremlinbox_ncgl_uk_2_0-1.4.0.dist-info/top_level.txt
pygremlinbox_ncgl_uk_2_0-1.4.0.dist-info/RECORD
