Metadata-Version: 2.4
Name: pygremlinbox-ncgl-uk-2-0
Version: 1.4.0
Summary: PyGremlinBox NCGL-UK-2.0 - Supply chain security testing module with Non-Commercial Government Licence UK v2.0
Author-email: Supply Chain Security Tester <simon@sigre.xyz>
Maintainer-email: Supply Chain Security Tester <simon@sigre.xyz>
License: NCGL-UK-2.0
Project-URL: Homepage, https://github.com/gocortexio/pygremlinbox
Project-URL: Repository, https://github.com/gocortexio/pygremlinbox.git
Project-URL: Issues, https://github.com/gocortexio/pygremlinbox/issues
Keywords: security,supply-chain,testing,ncgl-uk,non-commercial,licence
Classifier: Development Status :: 4 - Beta
Classifier: Intended Audience :: Developers
Classifier: License :: Other/Proprietary License
Classifier: Operating System :: OS Independent
Classifier: Programming Language :: Python :: 3
Classifier: Programming Language :: Python :: 3.8
Classifier: Programming Language :: Python :: 3.9
Classifier: Programming Language :: Python :: 3.10
Classifier: Programming Language :: Python :: 3.11
Classifier: Programming Language :: Python :: 3.12
Classifier: Topic :: Security
Classifier: Topic :: Software Development :: Testing
Requires-Python: >=3.8
License-File: LICENCE
Dynamic: license-file
